data/diann_dia/meta.csv
data/diann_dia/diann/report.parquet
data/sage_lfq/meta.csv
data/sage_lfq/sage/lfq.tsv
data/sage_lfq/sage/results.sage.tsv
data/sage_tmt/meta.csv
data/sage_tmt/sage/results.sage.tsv
data/sage_tmt/sage/tmt.tsv
docs/assets/custom.css
docs/assets/favicon.ico
docs/assets/favicon.svg
docs/assets/fig1b.svg
docs/assets/icon.svg
docs/assets/logo.svg
docs/assets/overview.svg
docs/assets/images/visualization_correlation_1.png
docs/assets/images/visualization_id_1.png
docs/assets/images/visualization_id_2.png
docs/assets/images/visualization_intensity_1.png
docs/assets/images/visualization_missingness_1.png
docs/assets/images/visualization_pca_1.png
docs/assets/images/visualization_upset_1.png
docs/assets/images/visualization_var_1.png
docs/assets/images/visualization_var_2.png
docs/how-it-works/batch_correction.md
docs/how-it-works/data.md
docs/how-it-works/dea.md
docs/how-it-works/filter.md
docs/how-it-works/inference.md
docs/how-it-works/normalization.md
docs/how-it-works/purity.md
docs/how-it-works/summarization.md
docs/how-it-works/visualization.md
docs/tutorials/dda-lfq.ipynb
docs/tutorials/dda-tmt.ipynb
docs/tutorials/dea.ipynb
docs/tutorials/dia-lfq.ipynb
docs/tutorials/flashlfq.ipynb
docs/tutorials/ptm.ipynb
docs/tutorials/quick_start.ipynb
docs/tutorials/2024_Fulcher/01_process_rna_data.ipynb
docs/tutorials/2024_Fulcher/02_process_protein_data.ipynb
docs/tutorials/2024_Fulcher/03_handle_multi-omics_data.ipynb
docs/tutorials/2024_Fulcher/Fig2B_WNN_UMAP.svg
docs/tutorials/2024_Fulcher/Fig2C_MOFA_R2.svg
docs/tutorials/2024_Fulcher/Fig2D_f2_prot.svg
docs/tutorials/2024_Fulcher/Fig2D_f2_rna.svg
docs/tutorials/2024_Fulcher/index.md
msmu/__init__.py
msmu/_version.py
msmu/logging_utils.py
msmu/msmu.py
msmu/_plotting/__init__.py
msmu/_plotting/_pdata.py
msmu/_plotting/_plots.py
msmu/_plotting/_ptypes.py
msmu/_plotting/_template.py
msmu/_plotting/_trace.py
msmu/_plotting/_utils.py
msmu/_preprocessing/__init__.py
msmu/_preprocessing/_filter.py
msmu-0.2.4.dist-info/licenses/LICENSE
msmu-0.2.4.dist-info/METADATA
msmu-0.2.4.dist-info/WHEEL
msmu-0.2.4.dist-info/top_level.txt
msmu-0.2.4.dist-info/RECORD
