Metadata-Version: 2.4
Name: msmu
Version: 0.2.4
Summary: BERTIS LC-MS/MS analysis library through MuData
Author-email: Hyung-wook Choi <hyungwook.choi@bertis.com>, Byeong-chan Lee <byeongchan.lee@bertis.com>
License: BSD 3-Clause License
Project-URL: Repository, https://github.com/bertis-informatics/msmu
Keywords: LC-MS/MS,Proteomics,Protein,Peptide,Mass Spectrometry
Requires-Python: >=3.8
License-File: LICENSE
Requires-Dist: mudata==0.3.2
Requires-Dist: anndata==0.12.0
Requires-Dist: biopython
Requires-Dist: plotly
Requires-Dist: statsmodels
Requires-Dist: scipy==1.15.3
Requires-Dist: scikit-learn
Requires-Dist: umap-learn
Requires-Dist: pyopenms
Requires-Dist: fastparquet
Provides-Extra: dev
Requires-Dist: pytest; extra == "dev"
Dynamic: license-file
